smear/__init__.py
smear/smear.py
utils/__init__.py
utils/data_extract.py
smear_data_api-1.0.4.dist-info/LICENSE
smear_data_api-1.0.4.dist-info/METADATA
smear_data_api-1.0.4.dist-info/WHEEL
smear_data_api-1.0.4.dist-info/top_level.txt
smear_data_api-1.0.4.dist-info/RECORD
